ddsmt/__init__.py
ddsmt/__main__.py
ddsmt/argparsemod.py
ddsmt/checker.py
ddsmt/cli.py
ddsmt/debug_utils.py
ddsmt/mutator_utils.py
ddsmt/mutators.py
ddsmt/mutators_arithmetic.py
ddsmt/mutators_boolean.py
ddsmt/mutators_bv.py
ddsmt/mutators_core.py
ddsmt/mutators_datatypes.py
ddsmt/mutators_fp.py
ddsmt/mutators_smtlib.py
ddsmt/mutators_strings.py
ddsmt/nodeio.py
ddsmt/nodes.py
ddsmt/options.py
ddsmt/progress.py
ddsmt/smtlib.py
ddsmt/strategy_ddmin.py
ddsmt/strategy_hierarchical.py
ddsmt/tmpfiles.py
ddsmt/version.py
ddsmt/tests/__init__.py
ddsmt/tests/test_mutators_arithmetic.py
ddsmt/tests/test_mutators_boolean.py
ddsmt/tests/test_mutators_bv.py
ddsmt/tests/test_mutators_core.py
ddsmt/tests/test_mutators_datatypes.py
ddsmt/tests/test_mutators_fp.py
ddsmt/tests/test_mutators_smtlib.py
ddsmt/tests/test_mutators_strings.py
ddsmt/tests/test_nodes.py
ddsmt/tests/test_options.py
ddsmt/tests/test_smtlib.py
ddsmt/tests/utils.py
ddsmt-2.0.6.data/scripts/smt2info
ddsmt-2.0.6.dist-info/licenses/LICENSE
ddsmt-2.0.6.dist-info/METADATA
ddsmt-2.0.6.dist-info/WHEEL
ddsmt-2.0.6.dist-info/entry_points.txt
ddsmt-2.0.6.dist-info/top_level.txt
ddsmt-2.0.6.dist-info/RECORD
