Metadata-Version: 2.4
Name: ddSMT
Version: 2.0.6
Summary: A delta debugger for SMT-LIBv2 files
Home-page: https://github.com/ddsmt/ddSMT
Download-URL: https://github.com/ddsmt/ddSMT
Author: The authors of ddSMT
License: MIT
Project-URL: Bug Tracker, https://github.com/ddsmt/ddSMT/issues
Project-URL: Documentation, https://ddsmt.readthedocs.io/
Project-URL: Source Code, https://github.com/ddsmt/ddSMT
Classifier: Intended Audience :: Science/Research
Classifier: License :: OSI Approved :: MIT License
Classifier: Programming Language :: Python :: 3.6
Classifier: Programming Language :: Python :: 3.7
Classifier: Programming Language :: Python :: 3.8
Classifier: Programming Language :: Python :: 3.9
Classifier: Programming Language :: Python :: 3.10
Classifier: Programming Language :: Python :: 3.11
Classifier: Programming Language :: Python :: 3.12
Classifier: Programming Language :: Python :: 3.13
Requires-Python: >=3.6
License-File: LICENSE
Requires-Dist: gprof2dot>=2019.11
Requires-Dist: importlib-metadata>=1.7; python_version < "3.8"
Dynamic: download-url
Dynamic: license-file
